{
  "$schema": "http://json-schema.org/draft-07/schema#",
  "title": "ICS_202 Auto Skeleton",
  "type": "object",
  "properties": {
    "incident": {
      "type": "object",
      "properties": {
        "name": {
          "type": "string"
        },
        "number": {
          "type": "string"
        }
      }
    },
    "operational_period": {
      "type": "object",
      "properties": {
        "label": {
          "type": "string"
        },
        "start": {
          "type": "string"
        },
        "end": {
          "type": "string"
        }
      }
    },
    "message": {
      "type": "object",
      "properties": {
        "to": {
          "type": "string"
        },
        "from": {
          "type": "string"
        },
        "subject": {
          "type": "string"
        },
        "body": {
          "type": "string"
        }
      }
    },
    "resources": {
      "type": "array",
      "items": {
        "type": "object",
        "properties": {
          "name": {
            "type": "string"
          }
        }
      }
    },
    "communications": {
      "type": "object",
      "properties": {
        "channels": {
          "type": "array",
          "items": {
            "type": "object"
          }
        }
      }
    },
    "activity_log": {
      "type": "object",
      "properties": {
        "entries": {
          "type": "array",
          "items": {
            "type": "object"
          }
        }
      }
    }
  }
}